{
  "resourceType" : "CodeSystem",
  "id" : "3c0612d1-c4f2-4958-815b-3702e0656388-8",
  "url" : "http://hl7.org/fhir/comparison/CodeSystem/3c0612d1-c4f2-4958-815b-3702e0656388-8",
  "name" : "UnionEclaireTypeContactCSAndEclaireTypeContactCS",
  "title" : "Union of Type de contact And Type de contact",
  "status" : "draft",
  "date" : "2023-10-20T09:00:31+00:00",
  "jurisdiction" : [{
    "coding" : [{
      "system" : "https://www.iso.org/obp/ui/fr/",
      "code" : "iso:code:3166:FR"
    }]
  }],
  "concept" : [{
    "code" : "PUB",
    "display" : "Publique / Public"
  },
  {
    "code" : "SCI",
    "display" : "Scientifique / Scientific"
  }]
}