{
  "resourceType" : "ValueSet",
  "id" : "e64540e8-13b9-477d-b83b-954647733499-75",
  "url" : "http://hl7.org/fhir/comparison/ValueSet/e64540e8-13b9-477d-b83b-954647733499-75",
  "name" : "IntersectionEclaireStudyPhaseSourceVSAndEclaireStudyPhaseSourceVS",
  "title" : "Intersection of Value Set de la phase de l'essai tel que définie dans la base ECLAIRE And Value Set de la phase de l'essai tel que définie dans la base ECLAIRE",
  "status" : "draft",
  "date" : "2024-01-10T17:41:52+00:00",
  "jurisdiction" : [{
    "coding" : [{
      "system" : "urn:iso:std:iso:3166",
      "code" : "FR",
      "display" : "FRANCE"
    }]
  }]
}