{
  "resourceType" : "CodeSystem",
  "id" : "6234490c-1eb0-428e-8c61-94060a1b4f3a-8",
  "url" : "http://hl7.org/fhir/comparison/CodeSystem/6234490c-1eb0-428e-8c61-94060a1b4f3a-8",
  "name" : "UnionEclaireTypeContactCSAndEclaireTypeContactCS",
  "title" : "Union of Type de contact And Type de contact",
  "status" : "draft",
  "date" : "2023-10-19T14:18:31+00:00",
  "concept" : [{
    "code" : "PUB",
    "display" : "Publique / Public"
  },
  {
    "code" : "SCI",
    "display" : "Scientifique / Scientific"
  }]
}