{
  "resourceType" : "CodeSystem",
  "id" : "24e2ce66-be3e-43ed-9a92-1d5a078d68b2-8",
  "url" : "http://hl7.org/fhir/comparison/CodeSystem/24e2ce66-be3e-43ed-9a92-1d5a078d68b2-8",
  "name" : "UnionEclaireTypeContactCSAndEclaireTypeContactCS",
  "title" : "Union of Type de contact And Type de contact",
  "status" : "draft",
  "date" : "2023-10-19T16:17:49+00:00",
  "concept" : [{
    "code" : "PUB",
    "display" : "Publique / Public"
  },
  {
    "code" : "SCI",
    "display" : "Scientifique / Scientific"
  }]
}